gtus/__init__.py
gtus/core.py
gtus/examples copy.py
gtus/examples.py
gtus-0.1.2.dist-info/LICENSE.txt
gtus-0.1.2.dist-info/METADATA
gtus-0.1.2.dist-info/WHEEL
gtus-0.1.2.dist-info/top_level.txt
gtus-0.1.2.dist-info/RECORD
