Metadata-Version: 2.2
Name: gtus
Version: 0.1.2
Summary: A Python package to collect and analyze Google Trends data for US states.
Home-page: https://github.com/leventbulut/gtus
Author: Levent Bulut
Author-email: Levent Bulut   <levent.bulut@unt.edu>
License: MIT License
Requires-Python: >=3.7
License-File: LICENSE.txt
Requires-Dist: pandas>=1.3.0
Requires-Dist: pytrends>=4.8.0
Requires-Dist: aiohttp>=3.8.0
Dynamic: author
Dynamic: home-page
Dynamic: requires-python
